README.rst
setup.py
sse.py
sse.egg-info/PKG-INFO
sse.egg-info/SOURCES.txt
sse.egg-info/dependency_links.txt
sse.egg-info/not-zip-safe
sse.egg-info/requires.txt
sse.egg-info/top_level.txt